pb_bss_eval/__init__.py
pb_bss_eval/evaluation/__init__.py
pb_bss_eval/evaluation/module_mir_eval.py
pb_bss_eval/evaluation/module_pesq.py
pb_bss_eval/evaluation/module_si_sdr.py
pb_bss_eval/evaluation/module_stoi.py
pb_bss_eval/evaluation/sxr_module.py
pb_bss_eval/evaluation/wrapper.py
pb_bss_eval-0.0.2.dist-info/LICENSE
pb_bss_eval-0.0.2.dist-info/METADATA
pb_bss_eval-0.0.2.dist-info/WHEEL
pb_bss_eval-0.0.2.dist-info/top_level.txt
pb_bss_eval-0.0.2.dist-info/RECORD
