Metadata-Version: 2.1
Name: pb-bss-eval
Version: 0.0.2
Summary: EM algorithms for integrated spatial and spectral models.
Home-page: UNKNOWN
Author: Lukas Drude
Author-email: mail@lukas-drude.de
License: UNKNOWN
Platform: UNKNOWN
Classifier: Programming Language :: Python :: 3.6
Requires-Dist: cached-property
Requires-Dist: einops
Requires-Dist: pystoi
Requires-Dist: mir-eval
Requires-Dist: pesq
